az_migrate_dep_visu/__init__.py
az_migrate_dep_visu/app.py
az_migrate_dep_visu/static/icon.png
az_migrate_dep_visu/static/icon_simplified.png
az_migrate_dep_visu/static/scripts.js
az_migrate_dep_visu/static/styles.css
az_migrate_dep_visu/templates/base.html
az_migrate_dep_visu/templates/result.html
az_migrate_dep_visu/templates/upload.html
az_migrate_dep_visu-0.1.3.dist-info/METADATA
az_migrate_dep_visu-0.1.3.dist-info/WHEEL
az_migrate_dep_visu-0.1.3.dist-info/entry_points.txt
az_migrate_dep_visu-0.1.3.dist-info/top_level.txt
az_migrate_dep_visu-0.1.3.dist-info/RECORD
