Metadata-Version: 2.2
Name: az-migrate-dep-visu
Version: 0.1.3
Summary: A web application to visualize network flows from Azure Migrate Dependency analysis CSV files.
Home-page: https://github.com/lrivallain/az-migrate-dep-visu
Author: Ludovic Rivallain
Author-email: ludovic.rivallain+pypi@gmail.com
Classifier: Programming Language :: Python :: 3
Classifier: License :: OSI Approved :: MIT License
Classifier: Operating System :: OS Independent
Requires-Python: >=3.6
Requires-Dist: Flask
Requires-Dist: Jinja2
Requires-Dist: Werkzeug
Requires-Dist: networkx[default]
Requires-Dist: pyvis
Dynamic: author
Dynamic: author-email
Dynamic: classifier
Dynamic: description
Dynamic: description-content-type
Dynamic: home-page
Dynamic: requires-dist
Dynamic: requires-python
Dynamic: summary
